jsonloggeriso8601datetime/__init__.py
jsonloggeriso8601datetime/__main__.py
jsonloggeriso8601datetime/jlidt.py
jsonloggeriso8601datetime/jsonloggerdictconfig.py
jsonloggeriso8601datetime/scripts/jlidtCli.py
jsonloggeriso8601datetime/scripts/jlidtQs.py
jsonloggeriso8601datetime/wrappers.py
jsonloggeriso8601datetime-3.0.0.dist-info/entry_points.txt
jsonloggeriso8601datetime-3.0.0.dist-info/LICENSE
jsonloggeriso8601datetime-3.0.0.dist-info/METADATA
jsonloggeriso8601datetime-3.0.0.dist-info/WHEEL
jsonloggeriso8601datetime-3.0.0.dist-info/RECORD
