Metadata-Version: 2.3
Name: jsonloggeriso8601datetime
Version: 3.0.0
Summary: Custom formatter for python-json-logger to iso8601 format timestamps.  includes default console and file logger config
License: MIT
Keywords: structured,console,logging,json,iso8601,configuration
Author: Joel Dodson
Author-email: joeldodson@gmail.com
Requires-Python: >=3.10
Classifier: Programming Language :: Python :: 3
Classifier: License :: OSI Approved :: MIT License
Classifier: Operating System :: OS Independent
Classifier: Development Status :: 6 - Mature
Classifier: Topic :: System :: Logging
Requires-Dist: python-json-logger (>=3.3.0)
Project-URL: Repository, https://github.com/joeldodson/jsonloggeriso8601datetime
